fastapi_core_utils/__init__.py
fastapi_core_utils/app_manager.py
fastapi_core_utils/database/README.md
fastapi_core_utils/database/__init__.py
fastapi_core_utils/database/db_manager.py
fastapi_core_utils/entity/README.md
fastapi_core_utils/entity/__init__.py
fastapi_core_utils/entity/base_entity.py
fastapi_core_utils/exceptions/__init__.py
fastapi_core_utils/exceptions/custom_exception.py
fastapi_core_utils/exceptions/handlers.py
fastapi_core_utils/middleware/__init__.py
fastapi_core_utils/middleware/cors_handler.py
fastapi_core_utils/middleware/response_handler.py
fastapi_core_utils/models/response.py
fastapi_core_utils/router/README.md
fastapi_core_utils/router/__init__.py
fastapi_core_utils/router/base_controller.py
fastapi_core_utils/router/decorators.py
fastapi_core_utils/router/registry.py
fastapi_core_utils/router/router_manager.py
fastapi_core_utils-0.0.6.dist-info/LICENSE
fastapi_core_utils-0.0.6.dist-info/METADATA
fastapi_core_utils-0.0.6.dist-info/WHEEL
fastapi_core_utils-0.0.6.dist-info/top_level.txt
fastapi_core_utils-0.0.6.dist-info/RECORD
