Metadata-Version: 2.2
Name: fastapi-core-utils
Version: 0.0.6
Summary: FastAPI utilities for rapid development
Author-email: 刘浩 <jiumengs@gmail.com>
License: MIT
Project-URL: Homepage, https://github.com/yourusername/fastapi-core-utils
Project-URL: Documentation, https://github.com/yourusername/fastapi-core-utils#readme
Project-URL: Repository, https://github.com/yourusername/fastapi-core-utils.git
Keywords: fastapi,utils,database,router
Classifier: Programming Language :: Python :: 3
Classifier: Programming Language :: Python :: 3.7
Classifier: Programming Language :: Python :: 3.8
Classifier: Programming Language :: Python :: 3.9
Classifier: Programming Language :: Python :: 3.10
Classifier: License :: OSI Approved :: MIT License
Classifier: Operating System :: OS Independent
Classifier: Framework :: FastAPI
Classifier: Intended Audience :: Developers
Classifier: Topic :: Software Development :: Libraries :: Python Modules
Requires-Python: >=3.7
License-File: LICENSE
Requires-Dist: fastapi>=0.68.0
Requires-Dist: tortoise-orm>=0.17.0
Requires-Dist: pyyaml>=5.4.1
